mcp_server_home_assistant/__init__.py
mcp_server_home_assistant/__main__.py
mcp_server_home_assistant/server.py
mcp_server_home_assistant-0.1.0.dist-info/METADATA
mcp_server_home_assistant-0.1.0.dist-info/WHEEL
mcp_server_home_assistant-0.1.0.dist-info/entry_points.txt
mcp_server_home_assistant-0.1.0.dist-info/licenses/LICENSE
mcp_server_home_assistant-0.1.0.dist-info/RECORD
