Metadata-Version: 2.3
Name: mcp-server-home-assistant
Version: 0.1.0
Summary: A Model Context Protocol Server for Home Assistant
Requires-Python: >=3.11
Requires-Dist: click>=8.1.7
Requires-Dist: hass-client>=1.2.0
Requires-Dist: mcp>=1.0.0
